{
   "blue": {
      "label": "blue",
      "imgSrc": "./media/img/blue.svg",
      "audioSrc": "./media/audio/blue.mp3"
   },
   "red": {
      "label": "red",
      "imgSrc": "./media/img/red.svg",
      "audioSrc": "./media/audio/red.mp3"
   },
   "grey": {
      "label": "grey",
      "imgSrc": "./media/img/grey.svg",
      "audioSrc": "./media/audio/grey.mp3"
   },
   "pink": {
      "label": "pink",
      "imgSrc": "./media/img/pink.svg",
      "audioSrc": "./media/audio/pink.mp3"
   },
   "green": {
      "label": "green",
      "imgSrc": "./media/img/green.svg",
      "audioSrc": "./media/audio/green.mp3"
   },
   "purple": {
      "label": "purple",
      "imgSrc": "./media/img/purple.svg",
      "audioSrc": "./media/audio/purple.mp3"
   },
   "yellow": {
      "label": "yellow",
      "imgSrc": "./media/img/yellow.svg",
      "audioSrc": "./media/audio/yellow.mp3"
   },
   "orange": {
      "label": "orange",
      "imgSrc": "./media/img/orange.svg",
      "audioSrc": "./media/audio/orange.mp3"
   },
   "black": {
      "label": "black",
      "imgSrc": "./media/img/black.svg",
      "audioSrc": "./media/audio/black.mp3"
   },
   "white": {
      "label": "white",
      "imgSrc": "./media/img/white.svg",
      "audioSrc": "./media/audio/white.mp3"
   },
   "america": {
      "label": "America",
      "imgSrc": "./media/img/Flag_of_the_United_States.svg",
      "audioSrc": "./media/audio/america.mp3"
   },
   "japan": {
      "label": "Japan",
      "imgSrc": "./media/img/Flag_of_Japan.svg",
      "audioSrc": "./media/audio/japan.mp3"
   },
   "australia": {
      "label": "Australia",
      "imgSrc": "./media/img/Flag_of_Australia.svg",
      "audioSrc": "./media/audio/australia.mp3"
   },
   "theUnitedKingdom": {
      "label": "the United Kingdom",
      "imgSrc": "./media/img/Flag_of_the_United_Kingdom.svg",
      "audioSrc": "./media/audio/theUnitedKingdom.mp3"
   },
   "theUK": {
      "label": "the U.K.",
      "imgSrc": "./media/img/Flag_of_the_United_Kingdom.svg",
      "audioSrc": "./media/audio/theUK.mp3"
   },
   "southAfrica": {
      "label": "South Africa",
      "imgSrc": "./media/img/Flag_of_South_Africa.svg",
      "audioSrc": "./media/audio/southAfrica.mp3"
   },
   "newZealand": {
      "label": "New Zealand",
      "imgSrc": "./media/img/Flag_of_New_Zealand.svg",
      "audioSrc": "./media/audio/newZealand.mp3"
   },
   "southKorea": {
      "label": "South Korea",
      "imgSrc": "./media/img/Flag_of_South_Korea.svg",
      "audioSrc": "./media/audio/southKorea.mp3"
   },
   "korea": {
      "label": "Korea",
      "imgSrc": "./media/img/Flag_of_South_Korea.svg",
      "audioSrc": "./media/audio/korea.mp3"
   },
   "india": {
      "label": "India",
      "imgSrc": "./media/img/Flag_of_India.svg",
      "audioSrc": "./media/audio/india.mp3"
   },
   "china": {
      "label": "China",
      "imgSrc": "./media/img/Flag_of_the_People's_Republic_of_China.svg",
      "audioSrc": "./media/audio/china.mp3"
   },
   "germany": {
      "label": "Germany",
      "imgSrc": "./media/img/Flag_of_Germany.svg",
      "audioSrc": "./media/audio/germany.mp3"
   },
   "one": {
      "label": "one",
      "imgSrc": "./media/img/one.svg",
      "audioSrc": "./media/audio/one.mp3"
   },
   "two": {
      "label": "two",
      "imgSrc": "./media/img/two.svg",
      "audioSrc": "./media/audio/two.mp3"
   },
   "three": {
      "label": "three",
      "imgSrc": "./media/img/three.svg",
      "audioSrc": "./media/audio/three.mp3"
   },
   "four": {
      "label": "four",
      "imgSrc": "./media/img/four.svg",
      "audioSrc": "./media/audio/four.mp3"
   },
   "five": {
      "label": "five",
      "imgSrc": "./media/img/five.svg",
      "audioSrc": "./media/audio/five.mp3"
   },
   "six": {
      "label": "six",
      "imgSrc": "./media/img/six.svg",
      "audioSrc": "./media/audio/six.mp3"
   },
   "seven": {
      "label": "seven",
      "imgSrc": "./media/img/seven.svg",
      "audioSrc": "./media/audio/seven.mp3"
   },
   "eight": {
      "label": "eight",
      "imgSrc": "./media/img/eight.svg",
      "audioSrc": "./media/audio/eight.mp3"
   },
   "nine": {
      "label": "nine",
      "imgSrc": "./media/img/nine.svg",
      "audioSrc": "./media/audio/nine.mp3"
   },
   "ten": {
      "label": "ten",
      "imgSrc": "./media/img/ten.svg",
      "audioSrc": "./media/audio/ten.mp3"
   },
   "eleven": {
      "label": "eleven",
      "imgSrc": "./media/img/eleven.svg",
      "audioSrc": "./media/audio/eleven.mp3"
   },
   "twelve": {
      "label": "twelve",
      "imgSrc": "./media/img/twelve.svg",
      "audioSrc": "./media/audio/twelve.mp3"
   },
   "thirteen": {
      "label": "thirteen",
      "imgSrc": "./media/img/thirteen.svg",
      "audioSrc": "./media/audio/thirteen.mp3"
   },
   "fourteen": {
      "label": "fourteen",
      "imgSrc": "./media/img/fourteen.svg",
      "audioSrc": "./media/audio/fourteen.mp3"
   },
   "fifteen": {
      "label": "fifteen",
      "imgSrc": "./media/img/fifteen.svg",
      "audioSrc": "./media/audio/fifteen.mp3"
   },
   "sixteen": {
      "label": "sixteen",
      "imgSrc": "./media/img/sixteen.svg",
      "audioSrc": "./media/audio/sixteen.mp3"
   },
   "seventeen": {
      "label": "seventeen",
      "imgSrc": "./media/img/seventeen.svg",
      "audioSrc": "./media/audio/seventeen.mp3"
   },
   "eighteen": {
      "label": "eighteen",
      "imgSrc": "./media/img/eighteen.svg",
      "audioSrc": "./media/audio/eighteen.mp3"
   },
   "nineteen": {
      "label": "nineteen",
      "imgSrc": "./media/img/nineteen.svg",
      "audioSrc": "./media/audio/nineteen.mp3"
   },
   "twenty": {
      "label": "twenty",
      "imgSrc": "./media/img/twenty.svg",
      "audioSrc": "./media/audio/twenty.mp3"
   },
   "happy": {
      "label": "happy",
      "imgSrc": "./media/img/happy.png",
      "audioSrc": "./media/audio/happy.mp3"
   },
   "nervous": {
      "label": "nervous",
      "imgSrc": "./media/img/nervous.png",
      "audioSrc": "./media/audio/nervous.mp3"
   },
   "sleepy": {
      "label": "sleepy",
      "imgSrc": "./media/img/sleepy.png",
      "audioSrc": "./media/audio/sleepy.mp3"
   },
   "tired": {
      "label": "tired",
      "imgSrc": "./media/img/tired.png",
      "audioSrc": "./media/audio/tired.mp3"
   },
   "thirsty": {
      "label": "thirsty",
      "imgSrc": "./media/img/thirsty.png",
      "audioSrc": "./media/audio/thirsty.mp3"
   },
   "hungry": {
      "label": "hungry",
      "imgSrc": "./media/img/hungry.png",
      "audioSrc": "./media/audio/hungry.mp3"
   },
   "sad": {
      "label": "sad",
      "imgSrc": "./media/img/sad.png",
      "audioSrc": "./media/audio/sad.mp3"
   },
   "angry": {
      "label": "angry",
      "imgSrc": "./media/img/angry.png",
      "audioSrc": "./media/audio/angry.mp3"
   },
   "sick": {
      "label": "sick",
      "imgSrc": "./media/img/sick.png",
      "audioSrc": "./media/audio/sick.mp3"
   },
   "hurt": {
      "label": "hurt",
      "imgSrc": "./media/img/hurt.png",
      "audioSrc": "./media/audio/hurt.mp3"
   },
   "great": {
      "label": "great",
      "imgSrc": "./media/img/great.png",
      "audioSrc": "./media/audio/great.mp3"
   },
   "good": {
      "label": "good",
      "imgSrc": "./media/img/good.png",
      "audioSrc": "./media/audio/good.mp3"
   },
   "fine": {
      "label": "fine",
      "imgSrc": "./media/img/fine.png",
      "audioSrc": "./media/audio/fine.mp3"
   },
   "soso": {
      "label": "so-so",
      "imgSrc": "./media/img/soso.png",
      "audioSrc": "./media/audio/soso.mp3"
   },
   "notSoGood": {
      "label": "not so good",
      "imgSrc": "./media/img/notSoGood.png",
      "audioSrc": "./media/audio/notSoGood.mp3"
   },
   "january": {
      "label": "January",
      "imgSrc": "./media/img/january.svg",
      "audioSrc": "./media/audio/january.mp3"
   },
   "february": {
      "label": "February",
      "imgSrc": "./media/img/february.svg",
      "audioSrc": "./media/audio/february.mp3"
   },
   "march": {
      "label": "March",
      "imgSrc": "./media/img/march.svg",
      "audioSrc": "./media/audio/march.mp3"
   },
   "april": {
      "label": "April",
      "imgSrc": "./media/img/april.svg",
      "audioSrc": "./media/audio/april.mp3"
   },
   "may": {
      "label": "May",
      "imgSrc": "./media/img/may.svg",
      "audioSrc": "./media/audio/may.mp3"
   },
   "june": {
      "label": "June",
      "imgSrc": "./media/img/june.svg",
      "audioSrc": "./media/audio/june.mp3"
   },
   "july": {
      "label": "July",
      "imgSrc": "./media/img/july.svg",
      "audioSrc": "./media/audio/july.mp3"
   },
   "august": {
      "label": "August",
      "imgSrc": "./media/img/august.svg",
      "audioSrc": "./media/audio/august.mp3"
   },
   "september": {
      "label": "September",
      "imgSrc": "./media/img/september.svg",
      "audioSrc": "./media/audio/september.mp3"
   },
   "october": {
      "label": "October",
      "imgSrc": "./media/img/october.svg",
      "audioSrc": "./media/audio/october.mp3"
   },
   "november": {
      "label": "November",
      "imgSrc": "./media/img/november.svg",
      "audioSrc": "./media/audio/november.mp3"
   },
   "december": {
      "label": "December",
      "imgSrc": "./media/img/december.svg",
      "audioSrc": "./media/audio/december.mp3"
   },
   "spring": {
      "label": "spring",
      "imgSrc": "./media/img/spring.png",
      "audioSrc": "./media/audio/spring.mp3"
   },
   "summer": {
      "label": "summer",
      "imgSrc": "./media/img/summer.png",
      "audioSrc": "./media/audio/summer.mp3"
   },
   "fall": {
      "label": "fall",
      "imgSrc": "./media/img/fall.png",
      "audioSrc": "./media/audio/fall.mp3"
   },
   "winter": {
      "label": "winter",
      "imgSrc": "./media/img/winter.png",
      "audioSrc": "./media/audio/winter.mp3"
   },
   "math": {
      "label": "math",
      "imgSrc": "./media/img/math.png",
      "audioSrc": "./media/audio/math.mp3"
   },
   "science": {
      "label": "science",
      "imgSrc": "./media/img/science.png",
      "audioSrc": "./media/audio/science.mp3"
   },
   "english": {
      "label": "English",
      "imgSrc": "./media/img/english.png",
      "audioSrc": "./media/audio/english.mp3"
   },
   "japanese": {
      "label": "Japanese",
      "imgSrc": "./media/img/japanese.png",
      "audioSrc": "./media/audio/japanese.mp3"
   },
   "socialStudies": {
      "label": "social studies",
      "imgSrc": "./media/img/socialStudies.png",
      "audioSrc": "./media/audio/socialStudies.mp3"
   },
   "artsAndCrafts": {
      "label": "arts and crafts",
      "imgSrc": "./media/img/artsAndCrafts.png",
      "audioSrc": "./media/audio/artsAndCrafts.mp3"
   },
   "homeEconomics": {
      "label": "home economics",
      "imgSrc": "./media/img/homeEconomics.png",
      "audioSrc": "./media/audio/homeEconomics.mp3"
   },
   "moralEducation": {
      "label": "moral education",
      "imgSrc": "./media/img/moralEducation.png",
      "audioSrc": "./media/audio/moralEducation.mp3"
   },
   "pe": {
      "label": "P.E.",
      "imgSrc": "./media/img/pe.png",
      "audioSrc": "./media/audio/pe.mp3"
   },
   "calligraphy": {
      "label": "calligraphy",
      "imgSrc": "./media/img/calligraphy.png",
      "audioSrc": "./media/audio/calligraphy.mp3"
   },
   "music": {
      "label": "music",
      "imgSrc": "./media/img/music.png",
      "audioSrc": "./media/audio/music.mp3"
   },
   "amusementPark": {
      "label": "amusement park",
      "imgSrc": "./media/img/amusementPark.png",
      "audioSrc": "./media/audio/amusementPark.mp3"
   },
   "aquarium": {
      "label": "aquarium",
      "imgSrc": "./media/img/aquarium.png",
      "audioSrc": "./media/audio/aquarium.mp3"
   },
   "cakeShop": {
      "label": "cake shop",
      "imgSrc": "./media/img/cakeShop.png",
      "audioSrc": "./media/audio/cakeShop.mp3"
   },
   "castle": {
      "label": "castle",
      "imgSrc": "./media/img/castle.png",
      "audioSrc": "./media/audio/castle.mp3"
   },
   "convenienceStore": {
      "label": "convenience store",
      "imgSrc": "./media/img/convenienceStore.png",
      "audioSrc": "./media/audio/convenienceStore.mp3"
   },
   "departmentStore": {
      "label": "department store",
      "imgSrc": "./media/img/departmentStore.png",
      "audioSrc": "./media/audio/departmentStore.mp3"
   },
   "flowerShop": {
      "label": "flower shop",
      "imgSrc": "./media/img/flowerShop.png",
      "audioSrc": "./media/audio/flowerShop.mp3"
   },
   "library": {
      "label": "library",
      "imgSrc": "./media/img/library.png",
      "audioSrc": "./media/audio/library.mp3"
   },
   "mountain": {
      "label": "mountain",
      "imgSrc": "./media/img/mountain.png",
      "audioSrc": "./media/audio/mountain.mp3"
   },
   "movieTheater": {
      "label": "movie theater",
      "imgSrc": "./media/img/movieTheater.png",
      "audioSrc": "./media/audio/movieTheater.mp3"
   },
   "museum": {
      "label": "museum",
      "imgSrc": "./media/img/museum.png",
      "audioSrc": "./media/audio/museum.mp3"
   },
   "park": {
      "label": "park",
      "imgSrc": "./media/img/park.png",
      "audioSrc": "./media/audio/park.mp3"
   },
   "policeStation": {
      "label": "police station",
      "imgSrc": "./media/img/policeStation.png",
      "audioSrc": "./media/audio/policeStation.mp3"
   },
   "postOffice": {
      "label": "post office",
      "imgSrc": "./media/img/postOffice.png",
      "audioSrc": "./media/audio/postOffice.mp3"
   },
   "restaurant": {
      "label": "restaurant",
      "imgSrc": "./media/img/restaurant.png",
      "audioSrc": "./media/audio/restaurant.mp3"
   },
   "river": {
      "label": "river",
      "imgSrc": "./media/img/river.png",
      "audioSrc": "./media/audio/river.mp3"
   },
   "school": {
      "label": "school",
      "imgSrc": "./media/img/school.png",
      "audioSrc": "./media/audio/school.mp3"
   },
   "sea": {
      "label": "sea",
      "imgSrc": "./media/img/sea.jpg",
      "audioSrc": "./media/audio/sea.mp3"
   },
   "zoo": {
      "label": "zoo",
      "imgSrc": "./media/img/zoo.png",
      "audioSrc": "./media/audio/zoo.mp3"
   }
}